markdown2ctags.py
markdown2ctags-0.3.3.dist-info/LICENSE.txt
markdown2ctags-0.3.3.dist-info/METADATA
markdown2ctags-0.3.3.dist-info/WHEEL
markdown2ctags-0.3.3.dist-info/entry_points.txt
markdown2ctags-0.3.3.dist-info/top_level.txt
markdown2ctags-0.3.3.dist-info/zip-safe
markdown2ctags-0.3.3.dist-info/RECORD
